pyquadraticsolution/__init__.py
pyquadraticsolution/solver.py
pyquadraticsolution-0.1.0.dist-info/License
pyquadraticsolution-0.1.0.dist-info/METADATA
pyquadraticsolution-0.1.0.dist-info/WHEEL
pyquadraticsolution-0.1.0.dist-info/top_level.txt
pyquadraticsolution-0.1.0.dist-info/RECORD
